aorun/__init__.py
aorun/activations.py
aorun/datasets.py
aorun/initializers.py
aorun/layers.py
aorun/losses.py
aorun/models.py
aorun/optimizers.py
aorun/utils.py
aorun-0.1.dist-info/DESCRIPTION.rst
aorun-0.1.dist-info/METADATA
aorun-0.1.dist-info/RECORD
aorun-0.1.dist-info/WHEEL
aorun-0.1.dist-info/metadata.json
aorun-0.1.dist-info/top_level.txt
tests/__init__.py
tests/context.py
tests/test_activations.py
tests/test_datasets.py
tests/test_initializers.py
tests/test_layers.py
tests/test_losses.py
tests/test_models.py
tests/test_optimizers.py
tests/test_utils.py
